<?xml version="1.0" encoding="UTF-8" standalone="yes"?>
<adapterConfiguration>
    <adapters>
        <adapter>
            <adapterType>
                <className>de.ingmbh.sphinx.online.adapter.history.HistoryAdapter</className>
                <description>Adapter for historization</description>
                <name>history</name>
                <userCreatable>true</userCreatable>
            </adapterType>
            <dbId>1</dbId>
            <description></description>
            <disabled>false</disabled>
            <domainName>local.soo-home</domainName>
            <name>history</name>
            <pollingIntervalMillis>-1</pollingIntervalMillis>
            <properties/>
            <releaseCode></releaseCode>
            <url>${project_loc}/config/adapter.soo_history_xml</url>
        </adapter>
        <adapter>
            <adapterType>
                <className>de.ingmbh.sphinx.online.adapter.simulation.SimulationAdapter</className>
                <description>Adapter for simulating a data source</description>
                <name>simulation</name>
                <userCreatable>true</userCreatable>
            </adapterType>
            <dbId>2</dbId>
            <description></description>
            <disabled>false</disabled>
            <domainName>local.soo-home</domainName>
            <name>simulation</name>
            <pollingIntervalMillis>-1</pollingIntervalMillis>
            <properties>
                <entry>
                    <key>overrideIdentifierPrefix</key>
                    <value></value>
                </entry>
            </properties>
            <releaseCode></releaseCode>
            <url>${project_loc}/config/simulation.soo_sim_xml</url>
        </adapter>
        <adapter>
            <adapterType>
                <className>de.ingmbh.sphinx.online.adapter.standalone.StandAloneAdapter</className>
                <description>Stand-alone Adapter for nodes without integration of an existing data source.</description>
                <name>stand-alone</name>
                <userCreatable>true</userCreatable>
            </adapterType>
            <dbId>3</dbId>
            <description></description>
            <disabled>false</disabled>
            <domainName>local.soo-home</domainName>
            <name>stand-alone</name>
            <pollingIntervalMillis>-1</pollingIntervalMillis>
            <properties>
                <entry>
                    <key>interval.millis</key>
                    <value>500</value>
                </entry>
            </properties>
            <releaseCode></releaseCode>
            <url>${project_loc}/config/standalone.soo_standalone_xml</url>
        </adapter>
    </adapters>
    <valueDefinitions>
        <valueDefinition>
            <adapterId>1</adapterId>
            <dataType>UNSPECIFIED</dataType>
            <enums/>
            <flags>0</flags>
            <historyBufferLimit>0</historyBufferLimit>
            <id>=$0</id>
            <mappedAdapter2>
                <dbId>1</dbId>
                <description></description>
                <disabled>false</disabled>
                <pollingIntervalMillis>-1</pollingIntervalMillis>
                <releaseCode></releaseCode>
                <url></url>
            </mappedAdapter2>
            <mappedId>.*</mappedId>
            <maxDataLength>-1</maxDataLength>
            <readable>true</readable>
            <valueType>VALUE</valueType>
            <writable>false</writable>
        </valueDefinition>
        <valueDefinition>
            <adapterId>2</adapterId>
            <dataType>UNSPECIFIED</dataType>
            <enums/>
            <flags>0</flags>
            <historyBufferLimit>0</historyBufferLimit>
            <id>=soo-home.$0</id>
            <mappedAdapter2>
                <dbId>2</dbId>
                <description></description>
                <disabled>false</disabled>
                <pollingIntervalMillis>-1</pollingIntervalMillis>
                <releaseCode></releaseCode>
                <url></url>
            </mappedAdapter2>
            <mappedId>.*</mappedId>
            <maxDataLength>-1</maxDataLength>
            <readable>true</readable>
            <valueType>VALUE</valueType>
            <writable>false</writable>
        </valueDefinition>
        <valueDefinition>
            <adapterId>3</adapterId>
            <dataType>UNSPECIFIED</dataType>
            <enums/>
            <flags>0</flags>
            <historyBufferLimit>0</historyBufferLimit>
            <id>=soo-home.$0</id>
            <mappedAdapter2>
                <dbId>3</dbId>
                <description></description>
                <disabled>false</disabled>
                <pollingIntervalMillis>-1</pollingIntervalMillis>
                <releaseCode></releaseCode>
                <url></url>
            </mappedAdapter2>
            <mappedId>.*</mappedId>
            <maxDataLength>-1</maxDataLength>
            <readable>true</readable>
            <valueType>VALUE</valueType>
            <writable>false</writable>
        </valueDefinition>
    </valueDefinitions>
</adapterConfiguration>
